grail_metabolism/.DS_Store
grail_metabolism/__init__.py
grail_metabolism/data/.DS_Store
grail_metabolism/data/pca_ats.pkl
grail_metabolism/data/pca_ats_single.pkl
grail_metabolism/data/pca_bonds.pkl
grail_metabolism/data/pca_bonds_single.pkl
grail_metabolism/data/smirks.txt
grail_metabolism/model/__init__.py
grail_metabolism/model/filter.py
grail_metabolism/model/generator.py
grail_metabolism/model/grail.py
grail_metabolism/model/train_model.py
grail_metabolism/model/wrapper.py
grail_metabolism/scripts/__init__.py
grail_metabolism/scripts/crutch.py
grail_metabolism/scripts/generator.py
grail_metabolism/scripts/install.py
grail_metabolism/tests/test_grail_metabolism.py
grail_metabolism/utils/__init__.py
grail_metabolism/utils/optuna.py
grail_metabolism/utils/preparation.py
grail_metabolism/utils/reaction_mapper.py
grail_metabolism/utils/transform.py
grail_metabolism-0.1.3.dist-info/METADATA
grail_metabolism-0.1.3.dist-info/WHEEL
grail_metabolism-0.1.3.dist-info/RECORD
