Metadata-Version: 2.1
Name: grail_metabolism
Version: 0.1.3
Summary: GRAIL is an open-source tool for drug metabolism prediction, based on graph neural networks and SMARTS reaction rules.
Author: doctawho42
Author-email: plomoshnovnikita00@gmail.com
Requires-Python: >=3.10,<4.0
Classifier: Programming Language :: Python :: 3
Classifier: Programming Language :: Python :: 3.10
Classifier: Programming Language :: Python :: 3.11
Classifier: Programming Language :: Python :: 3.12
Requires-Dist: matplotlib (>=3.9.2,<4.0.0)
Requires-Dist: multipledispatch (>=1.0.0,<2.0.0)
Requires-Dist: numpy (>=2.1.2,<3.0.0)
Requires-Dist: pandas (>=2.2.3,<3.0.0)
Requires-Dist: rdkit (>=2024.3.5,<2025.0.0)
Requires-Dist: scikit-learn (>=1.5.2,<2.0.0)
Requires-Dist: scipy (>=1.14.1,<2.0.0)
Requires-Dist: seaborn (>=0.13.2,<0.14.0)
Requires-Dist: torch (>=2.4.1,<3.0.0)
Requires-Dist: torch-geometric (>=2.6.1,<3.0.0)
